backoff.py
batchclient.py
llm_request.py
llm_response.py
msg.py
openai_provider.py
provider.py
token_bucket.py
usage.py
batchcal/__init__.py
batchcal-0.1.0.dist-info/METADATA
batchcal-0.1.0.dist-info/WHEEL
batchcal-0.1.0.dist-info/top_level.txt
batchcal-0.1.0.dist-info/RECORD
