Metadata-Version: 2.4
Name: batchcal
Version: 0.1.0
Summary: Tiny wrapper for batched multi-provider LLM calls
Author-email: Your Name <you@example.com>
License: MIT
Classifier: Programming Language :: Python :: 3
Classifier: Intended Audience :: Developers
Classifier: License :: OSI Approved :: MIT License
Classifier: Topic :: Software Development :: Libraries
Requires-Python: >=3.9
Requires-Dist: httpx>=0.27.0
Provides-Extra: dev
Requires-Dist: pytest>=7; extra == "dev"
Requires-Dist: pytest-asyncio>=0.23; extra == "dev"
